apple_container/__init__.py
apple_container/client.py
apple_container/errors.py
apple_container/models/__init__.py
apple_container/models/base.py
apple_container/models/container.py
apple_container/models/image.py
apple_container/models/network.py
apple_container/utils/__init__.py
apple_container/utils/platform.py
apple_container/xpc/__init__.py
apple_container/xpc/client.py
apple_container/xpc/routes.py
apple_container-0.0.2.dist-info/METADATA
apple_container-0.0.2.dist-info/WHEEL
apple_container-0.0.2.dist-info/RECORD
