Metadata-Version: 2.4
Name: apple-container
Version: 0.0.2
Summary: Python SDK for Apple Container with direct XPC
Author-email: Duy Huynh <vndee.huynh@gmail.com>
Keywords: python
Classifier: Intended Audience :: Developers
Classifier: Programming Language :: Python
Classifier: Programming Language :: Python :: 3.10
Classifier: Programming Language :: Python :: 3.11
Classifier: Programming Language :: Python :: 3.12
Classifier: Programming Language :: Python :: 3.13
Classifier: Topic :: Software Development :: Libraries :: Python Modules
Requires-Python: <4.0,>=3.9
Requires-Dist: pydantic>=2.11.5
Requires-Dist: pyobjc-core>=10.1
Requires-Dist: pyobjc-framework-cocoa>=10.1
Requires-Dist: typing-extensions>=4.0.0
